redshiftquery/GetOLsInTerm.sql
redshiftquery/GetTermsNoWinter.sql
redshiftquery/GetTermsWithWinter.sql
redshiftquery/__init__.py
redshiftquery/query.py
redshiftquery/terms.py
tests/__init__.py
tests/tests_myfunctions.py
redshiftquery-0.0.6.dist-info/LICENSE
redshiftquery-0.0.6.dist-info/METADATA
redshiftquery-0.0.6.dist-info/WHEEL
redshiftquery-0.0.6.dist-info/top_level.txt
redshiftquery-0.0.6.dist-info/RECORD
