Metadata-Version: 2.1
Name: redshiftquery
Version: 0.0.6
Summary: Tools for querying redshift
Home-page: https://github.com/StephenBoyer/RedshiftTools
Author: Stephen Boyer
Author-email: Stephen.B.Boyer@gmail.com
Classifier: Programming Language :: Python :: 3
Classifier: License :: OSI Approved :: MIT License
Classifier: Operating System :: OS Independent
Requires-Python: >=3.8.8
License-File: LICENSE
